fastermcp/__init__.py
fastermcp/client.py
fastermcp/protocol.py
fastermcp/server.py
fastermcp-0.1.0.dist-info/METADATA
fastermcp-0.1.0.dist-info/WHEEL
fastermcp-0.1.0.dist-info/RECORD
