Metadata-Version: 2.4
Name: fastermcp
Version: 0.1.0
Summary: A simple and intuitive library for building MCP (Model Context Protocol) servers and clients
Author: FasterMCP Team
Requires-Python: >=3.8
Requires-Dist: aiohttp>=3.8.0
Requires-Dist: fastapi>=0.68.0
Requires-Dist: pydantic>=2.0.0
Requires-Dist: python-dotenv>=0.19.0
Requires-Dist: uvicorn>=0.15.0
Provides-Extra: dev
Requires-Dist: black>=22.0.0; extra == 'dev'
Requires-Dist: isort>=5.0.0; extra == 'dev'
Requires-Dist: mypy>=0.910; extra == 'dev'
Requires-Dist: pytest>=7.0.0; extra == 'dev'
